{"format":2,"version":"5.1","globals":"bd2a88a9d5c568c8916bce971e999ec1","files":{"nerve_database_py":{"hash":"8b452fcd5055a828a87492f2662800d3","index":{"nums":[1,113,0,0,0,0,0],"html_filename":"nerve_database_py.html","relative_filename":"nerve/database.py"}},"nerve_parser_py":{"hash":"33c223da9b02b185c5699c2c56a9df65","index":{"nums":[1,118,0,0,0,0,0],"html_filename":"nerve_parser_py.html","relative_filename":"nerve/parser.py"}},"nerve_specification_base_py":{"hash":"608bb2d8d04b641324d53ae1dc724ff0","index":{"nums":[1,61,0,0,0,0,0],"html_filename":"nerve_specification_base_py.html","relative_filename":"nerve/specification_base.py"}},"nerve_specifications_py":{"hash":"2747e411b9a1528bebd85cda8838ff82","index":{"nums":[1,10,0,0,0,0,0],"html_filename":"nerve_specifications_py.html","relative_filename":"nerve/specifications.py"}},"nerve_tools_py":{"hash":"4c3ca08f000c8618f3a1645d9a1a54fe","index":{"nums":[1,68,0,0,0,0,0],"html_filename":"nerve_tools_py.html","relative_filename":"nerve/tools.py"}},"nerve_validators_py":{"hash":"29ae74b186ae2a45ffc8d12fdaff0dd4","index":{"nums":[1,62,11,0,0,0,0],"html_filename":"nerve_validators_py.html","relative_filename":"nerve/validators.py"}}}}